data_transformation_lib/.DS_Store
data_transformation_lib/__init__.py
data_transformation_lib/convolution.py
data_transformation_lib/transpose.py
data_transformation_lib/windowing.py
data_transformation_lib-0.1.0.dist-info/METADATA
data_transformation_lib-0.1.0.dist-info/WHEEL
data_transformation_lib-0.1.0.dist-info/RECORD
